{"nodes": [{"id": "frontend_src_app_app_automation_page_tsx", "label": "page.tsx", "file_type": "code", "source_file": "frontend\\src\\app\\(app)\\automation\\page.tsx", "source_location": "L1"}, {"id": "page_loaddata", "label": "loadData()", "file_type": "code", "source_file": "frontend\\src\\app\\(app)\\automation\\page.tsx", "source_location": "L38"}, {"id": "page_handleusetemplate", "label": "handleUseTemplate()", "file_type": "code", "source_file": "frontend\\src\\app\\(app)\\automation\\page.tsx", "source_location": "L53"}], "edges": [{"source": "frontend_src_app_app_automation_page_tsx", "target": "react", "relation": "imports_from", "confidence": "EXTRACTED", "source_file": "frontend\\src\\app\\(app)\\automation\\page.tsx", "source_location": "L3", "weight": 1.0}, {"source": "frontend_src_app_app_automation_page_tsx", "target": "lucide_react", "relation": "imports_from", "confidence": "EXTRACTED", "source_file": "frontend\\src\\app\\(app)\\automation\\page.tsx", "source_location": "L4", "weight": 1.0}, {"source": "frontend_src_app_app_automation_page_tsx", "target": "api", "relation": "imports_from", "confidence": "EXTRACTED", "source_file": "frontend\\src\\app\\(app)\\automation\\page.tsx", "source_location": "L8", "weight": 1.0}, {"source": "frontend_src_app_app_automation_page_tsx", "target": "page_loaddata", "relation": "contains", "confidence": "EXTRACTED", "source_file": "frontend\\src\\app\\(app)\\automation\\page.tsx", "source_location": "L38", "weight": 1.0}, {"source": "frontend_src_app_app_automation_page_tsx", "target": "page_handleusetemplate", "relation": "contains", "confidence": "EXTRACTED", "source_file": "frontend\\src\\app\\(app)\\automation\\page.tsx", "source_location": "L53", "weight": 1.0}], "raw_calls": [{"caller_nid": "page_loaddata", "callee": "all", "source_file": "frontend\\src\\app\\(app)\\automation\\page.tsx", "source_location": "L40"}, {"caller_nid": "page_loaddata", "callee": "get", "source_file": "frontend\\src\\app\\(app)\\automation\\page.tsx", "source_location": "L41"}, {"caller_nid": "page_loaddata", "callee": "get", "source_file": "frontend\\src\\app\\(app)\\automation\\page.tsx", "source_location": "L42"}, {"caller_nid": "page_loaddata", "callee": "setTemplates", "source_file": "frontend\\src\\app\\(app)\\automation\\page.tsx", "source_location": "L44"}, {"caller_nid": "page_loaddata", "callee": "setStats", "source_file": "frontend\\src\\app\\(app)\\automation\\page.tsx", "source_location": "L45"}, {"caller_nid": "page_loaddata", "callee": "error", "source_file": "frontend\\src\\app\\(app)\\automation\\page.tsx", "source_location": "L47"}, {"caller_nid": "page_loaddata", "callee": "setLoading", "source_file": "frontend\\src\\app\\(app)\\automation\\page.tsx", "source_location": "L49"}, {"caller_nid": "page_handleusetemplate", "callee": "setCreating", "source_file": "frontend\\src\\app\\(app)\\automation\\page.tsx", "source_location": "L54"}, {"caller_nid": "page_handleusetemplate", "callee": "post", "source_file": "frontend\\src\\app\\(app)\\automation\\page.tsx", "source_location": "L56"}, {"caller_nid": "page_handleusetemplate", "callee": "alert", "source_file": "frontend\\src\\app\\(app)\\automation\\page.tsx", "source_location": "L57"}, {"caller_nid": "page_handleusetemplate", "callee": "alert", "source_file": "frontend\\src\\app\\(app)\\automation\\page.tsx", "source_location": "L59"}, {"caller_nid": "page_handleusetemplate", "callee": "setCreating", "source_file": "frontend\\src\\app\\(app)\\automation\\page.tsx", "source_location": "L61"}]}